{"apiVersion": "v1", "data": {"config.yml": "connectIPVersion: v4\nports:\n  http: 80\n  tls: 853\nupstream:\n  default:\n    - tcp-tls:r4t7m0942c.cloudflare-gateway.com\n    - https://r4t7m0942c.cloudflare-gateway.com/dns-query\n    #- https://dns.quad9.net/dns-query\n    #- tcp-tls:dns.quad9.net\nbootstrapDns:\n  - tcp+udp:9.9.9.9\nblocking:\n  blackLists:\n    default:\n      - https://raw.githubusercontent.com/StevenBlack/hosts/master/hosts # adware + malware\n      - https://raw.githubusercontent.com/hagezi/dns-blocklists/main/domains/tif.txt # Threat Intelligence Feeds\n  clientGroupsBlock:\n    default:\n      - default\ncaching:\n  prefetching: true\n  minTime: \"600m\"\nprometheus:\n  enable: true\n  path: /metrics\n"}, "kind": "ConfigMap", "metadata": {"name": "blocky", "namespace": "blocky"}}