{"apiVersion": "networking.k8s.io/v1", "kind": "Ingress", "metadata": {"annotations": {"cert-manager.io/cluster-issuer": "letsencrypt-prod", "external-dns.alpha.kubernetes.io/hostname": "woodpecker.mordor.arleskog.se"}, "name": "woodpecker"}, "spec": {"ingressClassName": "nginx", "rules": [{"host": "woodpecker.mordor.arleskog.se", "http": {"paths": [{"backend": {"service": {"name": "woodpecker", "port": {"name": "http"}}}, "path": "/", "pathType": "Prefix"}]}}], "tls": [{"hosts": ["woodpecker.mordor.arleskog.se"], "secretName": "woodpecker-mordor-arleskog-se-cert"}]}}